csvmimesis/__init__.py
csvmimesis/cli.py
csvmimesis/mimesis_data_providers.py
csvmimesis/table_generator.py
csvmimesis/table_generator_sql.py
csvmimesis-0.2.dist-info/METADATA
csvmimesis-0.2.dist-info/RECORD
csvmimesis-0.2.dist-info/WHEEL
csvmimesis-0.2.dist-info/entry_points.txt
csvmimesis-0.2.dist-info/top_level.txt
