Metadata-Version: 2.1
Name: csvmimesis
Version: 0.2
Summary: Generate dummy tables using the mimesis data provider
Home-page: http://...
Author: jumbrich
Author-email: jueumb@gmail.com
License: mit
Platform: any
Classifier: Development Status :: 4 - Beta
Classifier: Programming Language :: Python
Requires-Dist: pandas
Requires-Dist: mimesis
Requires-Dist: sqlalchemy
